[
  {
    "title": "Financial Risk Management",
    "image": "/assets/financial-risk-management.webp",
    "slug": "financial-risk-management",
    "content": "<p>Implementing ThinkAct AI&reg; agentic AI customer service solution for a financial risk management company can significantly enhance operational efficiency, improve decision-making, and provide personalized support to clients. Here&rsquo;s how such a solution can be structured, leveraging insights from the search results:</p><p>Key Features of Agentic AI in Financial Risk Management</p><ol><li><strong>Real-Time Risk Monitoring</strong></li><ul><li><strong>Description</strong>: AI agents continuously monitor market conditions and risk factors, adapting to changes in real-time.</li><li><strong>Benefits</strong>: This capability allows financial institutions to respond quickly to emerging risks, reducing exposure and ensuring better service delivery to clients&nbsp;</li></ul><li><strong>Dynamic Risk Assessment</strong></li><ul><li><strong>Description</strong>: The AI system can autonomously adjust risk thresholds based on changing conditions and predict potential future risks.</li><li><strong>Benefits</strong>: By integrating multiple data sources, the AI provides comprehensive risk evaluations, enabling informed decision-making for clients&nbsp;</li></ul><li><strong>Fraud Detection and Prevention</strong></li><ul><li><strong>Description</strong>: Agentic AI can analyze transaction patterns and customer behaviors to identify anomalies indicative of fraud.</li><li><strong>Benefits</strong>: Proactive fraud detection minimizes financial losses and enhances client trust by addressing issues before they escalate&nbsp;</li></ul><li><strong>Personalized Financial Coaching</strong></li><ul><li><strong>Description</strong>: The AI can act as a personal financial advisor, offering tailored advice based on individual client profiles, financial history, and goals.</li><li><strong>Benefits</strong>: This personalized approach empowers clients to make informed decisions aligned with their risk appetite and financial objectives&nbsp;</li></ul><li><strong>Automated Compliance Monitoring</strong></li><ul><li><strong>Description</strong>: The AI solution can monitor regulatory changes and ensure that the company's operations remain compliant with industry standards.</li><li><strong>Benefits</strong>: Automated compliance checks reduce the risk of fines and reputational damage while enhancing operational efficiency&nbsp;</li></ul><li><strong>Data Integration and Analysis</strong></li><ul><li><strong>Description</strong>: Agentic AI can synthesize data from various sources, including market trends, economic indicators, and client transactions.</li><li><strong>Benefits</strong>: Comprehensive data analysis enables better risk profiling and more accurate assessments of potential threats&nbsp;</li></ul><li><strong>Client Interaction Automation</strong></li><ul><li><strong>Description</strong>: The AI can handle routine inquiries related to risk assessments, compliance issues, and general customer support.</li><li><strong>Benefits</strong>: Automating these interactions frees up human agents to focus on more complex tasks, improving overall productivity&nbsp;</li></ul><li><strong>Scenario Analysis and Forecasting</strong></li><ul><li><strong>Description</strong>: The system can conduct scenario analyses to assess potential outcomes based on varying market conditions.</li><li><strong>Benefits</strong>: This capability helps clients understand the implications of different strategies and make informed decisions about their investments&nbsp;</li></ul></ol><p>Benefits of Implementing Agentic AI in Financial Risk Management</p><ul><li><strong>Enhanced Decision-Making</strong>: With access to real-time data and predictive analytics, financial professionals can make more informed decisions quickly.</li><li><strong>Increased Efficiency</strong>: Automating routine tasks reduces operational costs while maintaining high service levels.</li><li><strong>Improved Client Satisfaction</strong>: Personalized support and proactive communication enhance the overall client experience, fostering loyalty.</li><li><strong>Reduced Risk Exposure</strong>: Continuous monitoring and dynamic assessments help mitigate risks effectively.</li></ul><p>Conclusion</p><p>ThinkAct AI&reg; agentic AI customer service solution tailored for a financial risk management company offers numerous advantages by automating processes, enhancing client interactions, and providing valuable insights. By leveraging these technologies, the company can improve efficiency, reduce costs, and deliver superior service while navigating the complexities of financial risk management effectively.</p><p>"
  },
  {
    "title": "Customer Service Solution",
    "image": "/assets/customer-serivices.webp",
    "slug": "customer-cervice-solution",
    "content": "<p>Implementing<strong>ThinkAct AI&reg;</strong>agentic AI customer service solution for a call center company can revolutionize how customer interactions are managed, enhancing efficiency and improving customer satisfaction. Here&rsquo;s a structured overview of such a solution based on the search results.</p><p>Key Features of Agentic AI in Call Centers</p><ol><li><strong>Autonomous Customer Interaction</strong></li><ul><li><strong>Description</strong>: Agentic AI can handle complex, multi-step customer interactions autonomously, making decisions and taking actions towards specific goals.</li><li><strong>Benefits</strong>: This reduces the need for human intervention in routine queries, allowing human agents to focus on more complex issues and improving overall service efficiency&nbsp;</li></ul><li><strong>24/7 Availability</strong></li><ul><li><strong>Description</strong>: AI agents provide round-the-clock support, ensuring that customers can get assistance at any time.</li><li><strong>Benefits</strong>: This enhances customer satisfaction by providing immediate responses to inquiries, regardless of the time of day&nbsp;</li></ul><li><strong>Seamless Integration with Existing Systems</strong></li><ul><li><strong>Description</strong>: The solution can integrate with various platforms like Salesforce, Avaya, and Genesys to access customer data and streamline interactions.</li><li><strong>Benefits</strong>: This integration allows for accurate and efficient resolutions by enabling AI agents to pull relevant information quickly&nbsp;</li></ul><li><strong>Personalized Customer Experiences</strong></li><ul><li><strong>Description</strong>: Agentic AI uses real-time context to deliver hyper-personalized interactions based on individual customer profiles and histories.</li><li><strong>Benefits</strong>: Personalized service improves engagement and increases the likelihood of successful resolutions, fostering customer loyalty&nbsp;</li></ul><li><strong>Proactive Issue Resolution</strong></li><ul><li><strong>Description</strong>: The AI can identify common issues and proactively address them before they escalate into larger problems.</li><li><strong>Benefits</strong>: This proactive approach enhances customer satisfaction by resolving potential concerns quickly&nbsp;</li></ul><li><strong>Collaborative AI Workforce</strong></li><ul><li><strong>Description</strong>: Agentic AI works alongside human agents, facilitating smooth handovers when escalation is required.</li><li><strong>Benefits</strong>: This collaboration creates a unified customer service ecosystem that enhances overall efficiency and service quality&nbsp;</li></ul><li><strong>Data-Driven Insights and Analytics</strong></li><ul><li><strong>Description</strong>: The AI collects and analyzes data from customer interactions to provide actionable insights for improving service quality.</li><li><strong>Benefits</strong>: Continuous improvement based on data-driven insights leads to enhanced decision-making and strategic planning within the call center&nbsp;</li></ul><li><strong>Automated Quality Assurance</strong></li><ul><li><strong>Description</strong>: The system can analyze calls for compliance and performance metrics, providing feedback to agents for improvement.</li><li><strong>Benefits</strong>: This ensures consistent service quality while identifying training needs for staff&nbsp;</li></ul></ol><p>Benefits of Implementing Agentic AI in Call Centers</p><ul><li><strong>Increased Efficiency</strong>: Automating routine inquiries allows call centers to handle higher volumes of calls without increasing operational costs.</li><li><strong>Cost Reduction</strong>: By reducing reliance on human agents for basic inquiries, companies can lower labor costs while maintaining high service levels.</li><li><strong>Improved Customer Satisfaction</strong>: Faster response times and personalized support lead to higher levels of customer satisfaction and loyalty.</li><li><strong>Scalability</strong>: The flexibility of agentic AI solutions enables call centers to scale operations effectively during peak demand periods without compromising service quality.</li></ul><p>Conclusion</p><p><strong>ThinkAct AI</strong>&reg; agentic AI customer service solution tailored for a call center company offers numerous advantages by automating processes, enhancing customer interactions, and providing valuable insights. By leveraging these technologies, call centers can improve efficiency, reduce costs, and deliver superior service while meeting the evolving demands of customers in today's fast-paced environment.</p>"
  },
  {
    "title": "EdTech company",
    "image": "/assets/edtech.webp",
    "slug": "edTech-company",
    "content": "<p>Implementing<strong>ThinkAct AI</strong>&reg; agentic AI customer service solution for an EdTech company can significantly enhance student engagement, streamline administrative processes, and improve overall service quality. Here&rsquo;s how such a solution can be structured, drawing from the insights provided in the search results.</p><p>Key Features of Agentic AI in EdTech</p><ol><li><strong>24/7 Student Support</strong></li><ul><li><strong>Description</strong>: AI chatbots provide round-the-clock assistance for student inquiries related to course materials, enrollment processes, and technical support.</li><li><strong>Benefits</strong>: Immediate access to information reduces wait times and enhances the student experience by ensuring support is available whenever needed.</li></ul><li><strong>Personalized Learning Assistance</strong></li><ul><li><strong>Description</strong>: The AI can analyze student data to offer tailored recommendations for courses, resources, and study materials based on individual learning styles and performance.</li><li><strong>Benefits</strong>: Personalized interactions foster deeper engagement and help students navigate their educational paths more effectively.</li></ul><li><strong>Automated Enrollment Management</strong></li><ul><li><strong>Description</strong>: The AI can automate the enrollment process, guiding students through application forms and providing real-time updates on their application status.</li><li><strong>Benefits</strong>: This reduces administrative burdens on staff and ensures a smoother onboarding experience for new students.</li></ul><li><strong>Proactive Communication</strong></li><ul><li><strong>Description</strong>: AI can send automated reminders for upcoming deadlines (e.g., assignment submissions, exam dates) and alerts about course updates.</li><li><strong>Benefits</strong>: Proactive communication keeps students informed and helps them stay on track with their studies.</li></ul><li><strong>Feedback Collection and Analysis</strong></li><ul><li><strong>Description</strong>: The AI can gather feedback from students about courses and instructors, analyzing sentiment to identify areas for improvement.</li><li><strong>Benefits</strong>: Understanding student feedback allows institutions to adapt their offerings to better meet learner needs, enhancing overall satisfaction.</li></ul><li><strong>Knowledge Base Management</strong></li><ul><li><strong>Description</strong>: An AI-powered knowledge base can provide students with instant access to FAQs, tutorials, and troubleshooting guides related to the platform or course content.</li><li><strong>Benefits</strong>: A comprehensive knowledge base empowers students to find answers independently, reducing the volume of inquiries directed to human agents.</li></ul><li><strong>Integration with Learning Management Systems (LMS)</strong></li><ul><li><strong>Description</strong>: The agentic AI solution can integrate seamlessly with existing LMS platforms to provide real-time data access for both students and educators.</li><li><strong>Benefits</strong>: This integration enhances the user experience by providing accurate information quickly and facilitating smooth communication between students and instructors.</li></ul><li><strong>Performance Tracking and Reporting</strong></li><ul><li><strong>Description</strong>: The AI can monitor student progress in real-time, providing insights into performance trends and identifying at-risk students who may need additional support.</li><li><strong>Benefits</strong>: Early identification of challenges enables timely interventions, improving student retention rates.</li></ul></ol><p>Benefits of Implementing Agentic AI in EdTech</p><ul><li><strong>Enhanced Student Experience</strong>: With faster response times and personalized support, students are more likely to have positive experiences with the educational institution.</li><li><strong>Increased Operational Efficiency</strong>: Automating routine tasks allows staff to focus on higher-value activities, improving overall productivity within the organization.</li><li><strong>Cost Savings</strong>: Reducing reliance on human agents for basic inquiries lowers operational costs while maintaining high service levels.</li><li><strong>Higher Retention Rates</strong>: Providing exceptional service through proactive communication fosters student loyalty and retention.</li></ul><p>Conclusion</p><p><strong>ThinkAct AI</strong>&reg; agentic AI customer service solution tailored for an EdTech company offers numerous advantages by automating processes, enhancing student interactions, and providing valuable insights. By leveraging these technologies, educational institutions can improve efficiency, reduce costs, and deliver superior service while supporting students' learning journeys effectively.</p>"
  } 
   
]
